ewoksxrpd/__init__.py
ewoksxrpd/init_matplotlib.py
ewoksxrpd/pyfai_api.py
ewoksxrpd/gui/__init__.py
ewoksxrpd/gui/forms.py
ewoksxrpd/gui/image_viewer.py
ewoksxrpd/gui/plots.py
ewoksxrpd/gui/serialize.py
ewoksxrpd/gui/trigger_widget.py
ewoksxrpd/tasks/__init__.py
ewoksxrpd/tasks/ascii.py
ewoksxrpd/tasks/background.py
ewoksxrpd/tasks/base_integrate.py
ewoksxrpd/tasks/bliss.py
ewoksxrpd/tasks/calibrate.py
ewoksxrpd/tasks/convolution.py
ewoksxrpd/tasks/data_access.py
ewoksxrpd/tasks/diagnostics.py
ewoksxrpd/tasks/integrate.py
ewoksxrpd/tasks/log.py
ewoksxrpd/tasks/mask.py
ewoksxrpd/tasks/morphology.py
ewoksxrpd/tasks/multi_geometry_integrate.py
ewoksxrpd/tasks/nexus.py
ewoksxrpd/tasks/pyfaiconfig.py
ewoksxrpd/tasks/save_images.py
ewoksxrpd/tasks/subtract_pattern.py
ewoksxrpd/tasks/sum.py
ewoksxrpd/tasks/worker.py
ewoksxrpd/tasks/utils/__init__.py
ewoksxrpd/tasks/utils/ascii_utils.py
ewoksxrpd/tasks/utils/calibrate_utils.py
ewoksxrpd/tasks/utils/data_utils.py
ewoksxrpd/tasks/utils/integrate_utils.py
ewoksxrpd/tasks/utils/nexus_utils.py
ewoksxrpd/tasks/utils/pyfai_utils.py
ewoksxrpd/tasks/utils/sum_utils.py
ewoksxrpd/tasks/utils/xrpd_utils.py
ewoksxrpd/tasks/utils/zip_utils.py
ewoksxrpd/tests/__init__.py
ewoksxrpd/tests/conftest.py
ewoksxrpd/tests/test_ascii.py
ewoksxrpd/tests/test_background.py
ewoksxrpd/tests/test_bliss_integrate.py
ewoksxrpd/tests/test_bliss_integrate_no_save.py
ewoksxrpd/tests/test_calibrate.py
ewoksxrpd/tests/test_calint_workflow.py
ewoksxrpd/tests/test_darkflat.py
ewoksxrpd/tests/test_data_utils.py
ewoksxrpd/tests/test_integrate.py
ewoksxrpd/tests/test_log.py
ewoksxrpd/tests/test_mask.py
ewoksxrpd/tests/test_multi_geometry.py
ewoksxrpd/tests/test_multi_integrate.py
ewoksxrpd/tests/test_nexus.py
ewoksxrpd/tests/test_nexus_integrated.py
ewoksxrpd/tests/test_pyfai_utils.py
ewoksxrpd/tests/test_pyfaiconfig.py
ewoksxrpd/tests/test_save_images.py
ewoksxrpd/tests/test_subtract_pattern.py
ewoksxrpd/tests/test_sum.py
ewoksxrpd/tests/test_worker.py
ewoksxrpd-1.6.0.dist-info/licenses/LICENSE.md
ewoksxrpd-1.6.0.dist-info/METADATA
ewoksxrpd-1.6.0.dist-info/WHEEL
ewoksxrpd-1.6.0.dist-info/entry_points.txt
ewoksxrpd-1.6.0.dist-info/top_level.txt
ewoksxrpd-1.6.0.dist-info/RECORD
