Metadata-Version: 2.4
Name: ewoksxrpd
Version: 1.6.0
Summary: Data processing workflows for SAXS/WAXS
Author-email: ESRF <dau-pydev@esrf.fr>
License: # MIT License
Project-URL: Homepage, https://gitlab.esrf.fr/workflow/ewoksapps/ewoksxrpd/
Project-URL: Documentation, https://ewoksxrpd.readthedocs.io/
Project-URL: Repository, https://gitlab.esrf.fr/workflow/ewoksapps/ewoksxrpd/
Project-URL: Issues, https://gitlab.esrf.fr/workflow/ewoksapps/ewoksxrpd/issues
Project-URL: Changelog, https://gitlab.esrf.fr/workflow/ewoksapps/ewoksxrpd/-/blob/main/CHANGELOG.md
Keywords: orange3 add-on,ewoks
Classifier: Intended Audience :: Science/Research
Classifier: License :: OSI Approved :: MIT License
Classifier: Programming Language :: Python :: 3
Requires-Python: >=3.8
License-File: LICENSE.md
Requires-Dist: numpy
Requires-Dist: scipy
Requires-Dist: silx!=2.1.0,>=1.1.0
Requires-Dist: pyopencl
Requires-Dist: pyfai>=2024.1
Requires-Dist: numexpr!=2.8.6
Requires-Dist: ewoksdata>=1.2.0
Requires-Dist: ewokscore
Requires-Dist: ewoksorange>=3.0.0rc1
Requires-Dist: fabio
Requires-Dist: h5py
Requires-Dist: packaging
Requires-Dist: redis!=5.3.0b1,!=5.3.0b3
Provides-Extra: online
Requires-Dist: ewoksdata[online]; extra == "online"
Provides-Extra: test
Requires-Dist: pytest>=7; extra == "test"
Requires-Dist: matplotlib>=3.1; extra == "test"
Requires-Dist: pyqt5; extra == "test"
Provides-Extra: dev
Requires-Dist: ewoksxrpd[test]; extra == "dev"
Requires-Dist: black>=25; extra == "dev"
Requires-Dist: flake8>=4; extra == "dev"
Requires-Dist: isort; extra == "dev"
Provides-Extra: doc
Requires-Dist: ewoksxrpd[test]; extra == "doc"
Requires-Dist: sphinx>=4.5; extra == "doc"
Requires-Dist: sphinx-autodoc-typehints>=1.16; extra == "doc"
Requires-Dist: pydata_sphinx_theme; extra == "doc"
Requires-Dist: ewokssphinx>=0.3.0; extra == "doc"
Requires-Dist: sphinx-copybutton; extra == "doc"
Dynamic: license-file
